README
setup.py
webcrawler
pywebcrawler/__init__.py
webcrawler.egg-info/PKG-INFO
webcrawler.egg-info/SOURCES.txt
webcrawler.egg-info/dependency_links.txt
webcrawler.egg-info/requires.txt
webcrawler.egg-info/top_level.txt