Metadata-Version: 1.0
Name: webcrawler
Version: 0.3
Summary: Web Crawler
Home-page: https://github.com/gamezdaniel/mswl-dt-2013/blob/master/webcrawler
Author: Daniel Gamez
Author-email: d.gamez@alumnos.urjc.es
License: BSD 2-clause
Keywords: web crawler spider
Platform: UNKNOWN
